networkx_gdf/__init__.py
networkx_gdf/__version__.py
networkx_gdf/networkx_gdf.py
networkx_gdf-1.5.3.dist-info/LICENSE.md
networkx_gdf-1.5.3.dist-info/METADATA
networkx_gdf-1.5.3.dist-info/WHEEL
networkx_gdf-1.5.3.dist-info/top_level.txt
networkx_gdf-1.5.3.dist-info/RECORD
