Metadata-Version: 2.1
Name: networkx-gdf
Version: 1.5.3
Summary: Python package to read and write NetworkX graphs in GDF (Graph Data Format).
Author-email: Nelson Aloysio Reis de Almeida Passos <nelson.reis@phd.unipi.it>
Project-URL: Homepage, https://pypi.org/p/networkx-gdf/
Project-URL: Documentation, https://networkx-gdf.readthedocs.io
Project-URL: Repository, https://github.com/nelsonaloysio/networkx-gdf
Project-URL: Issues, https://github.com/nelsonaloysio/networkx-gdf/issues
Project-URL: Changelog, https://github.com/nelsonaloysio/networkx-gdf/blob/main/CHANGELOG.md
Keywords: Network,Graph,GDF
Classifier: Development Status :: 5 - Production/Stable
Classifier: Intended Audience :: Developers
Classifier: Intended Audience :: Information Technology
Classifier: License :: OSI Approved :: BSD License
Classifier: Programming Language :: Python :: 3
Classifier: Topic :: Scientific/Engineering :: Information Analysis
Classifier: Topic :: Software Development :: Libraries :: Python Modules
Requires-Python: >=3.7
License-File: LICENSE.md
Requires-Dist: networkx >=2.1
Requires-Dist: pandas >=1.1.0
Provides-Extra: docs
Requires-Dist: sphinx-autodoc-typehints >=1.23.0 ; extra == 'docs'
Requires-Dist: sphinx-rtd-theme >=2.0.0 ; extra == 'docs'
